emitime/__init__.py
emitime/__init__.pyi
emitime/__version__.py
emitime/__version__.pyi
emitime/base.py
emitime/base.pyi
emitime/conversion.py
emitime/conversion.pyi
emitime/py.typed
emitime/tools.py
emitime/tools.pyi
emitime/parser/__init__.py
emitime/parser/__init__.pyi
emitime/parser/ram.py
emitime/parser/ram.pyi
emitime-0.2.13.dist-info/LICENSE
emitime-0.2.13.dist-info/METADATA
emitime-0.2.13.dist-info/WHEEL
emitime-0.2.13.dist-info/top_level.txt
emitime-0.2.13.dist-info/RECORD
