Metadata-Version: 2.1
Name: emitime
Version: 0.2.13
Home-page: https://github.com/rilshok/emitime
Author: Vladislav A. Proskurov
Author-email: rilshok@pm.me
License: MIT
Classifier: Programming Language :: Python
Classifier: Programming Language :: Python :: 3
Classifier: Programming Language :: Python :: 3.6
Classifier: License :: OSI Approved :: MIT License
Classifier: Operating System :: OS Independent
Requires-Python: >=3.6
License-File: LICENSE
Requires-Dist: pytest
Requires-Dist: plum-dispatch
Requires-Dist: xxhash
Requires-Dist: types-xxhash
